{
  "categories": {
    "Hoodies": [
      {
        "id": "2",
        "name": "Washed All Over Cherub Hoodie",
        "images": [
          "https://thehangerpakistan.com/cdn/shop/files/4BE86E59-40F3-4EAB-9493-4917B2C1F9F4_720x900.jpg?v=1702912946",
          "https://thehangerpakistan.com/cdn/shop/files/6EB28359-07E3-4FAD-859D-21A2B53C4B07_720x900.jpg?v=1702912947",
          "https://thehangerpakistan.com/cdn/shop/files/0169887A-B72F-4ED5-BF2B-ACD77D02184C_720x900.jpg?v=1702920310"
        ],
        "price": 1799.0,
        "inStock": false,
        "type": "Casual",
        "reviews": 2,
        "productDescription": "Super soft and ultra comfortable washed oversized hoodie with drop shoulders featuring a screen print graphics."
      },
      {
        "id": "3",
        "name": "Washed Legacy Hoodie",
        "images": [
          "https://thehangerpakistan.com/cdn/shop/files/IMG-3870_720x900.jpg?v=1702913498",
          "https://thehangerpakistan.com/cdn/shop/files/6BEEDF8B-1DEF-44C0-94F8-14039EF43020_720x900.jpg?v=1702913498",
          "https://thehangerpakistan.com/cdn/shop/files/601F5323-A631-40A0-9320-70F34104B152_720x900.jpg?v=1702913498"
        ],
        "price": 1900.0,
        "inStock": false,
        "type": "Casual",
        "reviews": 3,
        "productDescription": "Super soft and ultra comfortable washed oversized hoodie with drop shoulders featuring a screen print graphics."
      },
      {
        "id": "4",
        "name": "MotorChamptions Hoodie",
        "images": [
          "https://thehangerpakistan.com/cdn/shop/files/IMG-3632_720x900.jpg?v=1702822136",
          "https://thehangerpakistan.com/cdn/shop/files/E191162F-2488-46DC-99C6-FA1F157D64EF_720x900.jpg?v=1702822136",
          "https://thehangerpakistan.com/cdn/shop/files/EAD38E11-D78C-42B8-9176-7C97DB4095E9_720x900.jpg?v=1702822137"
        ],
        "price": 1799.0,
        "inStock": true,
        "type": "Casual",
        "reviews": 8,
        "productDescription": "Super soft and ultra comfortable washed oversized hoodie with drop shoulders & concealed pockets featuring a screen print graphics."
      },
      {
        "id": "5",
        "name": "All Over Cherub Hoodie (Grey)",
        "images": [
          "https://thehangerpakistan.com/cdn/shop/files/IMG-4427_720x720.png?v=1705575721"
        ],
        "price": 1700.0,
        "inStock": true,
        "type": "Casual",
        "reviews": 3,
        "productDescription": "Super soft and ultra comfortable oversized hoodie with drop shoulders featuring a screen print graphics."
      }
    ],
    "Outerwear": [
      {
        "id": "6",
        "name": "Varisty VI",
        "images": [
          "https://thehangerpakistan.com/cdn/shop/files/01E8E6E3-5241-4719-BE7B-7C8640E49B6B_900x900.jpg?v=1704332674",
          "https://thehangerpakistan.com/cdn/shop/files/E76EB7AB-D11D-4D39-AFD9-573971293F87_900x900.jpg?v=1704366592",
          "https://thehangerpakistan.com/cdn/shop/files/4E05B46C-C86E-4E72-9A3A-77B2F151D9FC_900x900.jpg?v=1704366593"
        ],
        "price": 3500.0,
        "inStock": true,
        "type": "Casual",
        "reviews": 2,
        "productDescription": "Introducing the Varsity Jacket. This varsity jacket has an oversized fit, with chenille embroidered season artwork to the front. It has embroidery detailed sleeve artwork on one side, stand collar and ribbed sleeves and hem."
      }
    ],
    "Bottoms": [
      {
        "id": "7",
        "name": "Black Cargo VII",
        "images": [
          "https://thehangerpakistan.com/cdn/shop/files/8D6D8A09-83BD-4666-89AD-BE222B705B3F_720x900.jpg?v=1702839346",
          "https://thehangerpakistan.com/cdn/shop/files/IMG-4087_720x900.jpg?v=1703459332",
          "https://thehangerpakistan.com/cdn/shop/files/IMG-4088_720x900.jpg?v=1703459485"
        ],
        "price": 2699.0,
        "inStock": true,
        "type": "cargos",
        "reviews": 19,
        "productDescription": "Wear-with-everything pants in our signature straight fit. Designed in comfortable drill fabric made with button waist band, Advanced Stretch, Featuring button waist, cargo pockets and back pockets."
      },
      {
        "id": "8",
        "name": "Black Piping Trousers",
        "images": [
          "https://thehangerpakistan.com/cdn/shop/files/B673D8F2-513C-4646-8035-DDCE045BDF60_720x900.jpg?v=1704243899",
          "https://thehangerpakistan.com/cdn/shop/files/09739CC1-1187-49FE-885F-020AB12EDD7A_720x900.jpg?v=1704243899",
          "https://thehangerpakistan.com/cdn/shop/files/7E2CC732-ACD1-4736-B55F-BEB7E7F2C680_720x900.jpg?v=1703716201"
        ],
        "price": 1800.0,
        "inStock": true,
        "type": "trousers",
        "reviews": 5,
        "productDescription": "Wear-with-everything pants in our signature straight fit. Designed in comfortable drill fabric made with button waist band, Advanced Stretch, Featuring button waist, cargo pockets and back pockets."
      },
      {
        "id": "9",
        "name": "Washed Pleated Trousers",
        "images": [
          "https://thehangerpakistan.com/cdn/shop/files/9C589F63-3DDF-4F08-ACCB-2ECF0639A3A1_720x900.jpg?v=1702914590",
          "https://thehangerpakistan.com/cdn/shop/files/6BE878CD-ADDE-481E-B9E0-F114B838B547_720x900.jpg?v=1702914591",
          "https://thehangerpakistan.com/cdn/shop/files/57DB4895-15B7-4ED5-8E85-BB5B91208EF9_720x900.jpg?v=1702914591"
        ],
        "price": 1800.0,
        "inStock": true,
        "type": "trousers",
        "reviews": 4,
        "productDescription": "Wear-with-everything pants in our signature straight fit. Designed in comfortable Fleece fabric made with Advanced Stretch, Featuring cross pockets."
      },
      {
        "id": "10",
        "name": "Olive Green Cargo Pants",
        "images": [
          "https://thehangerpakistan.com/cdn/shop/products/image_a08eca91-ffd7-4d5e-a1ce-f44def47b638_720x900.jpg?v=1680072263",
          "https://thehangerpakistan.com/cdn/shop/products/image_96dd391d-7d40-4220-8445-f51c7412a1c5_720x900.jpg?v=1680072263",
          "https://thehangerpakistan.com/cdn/shop/products/image_c6b9fe50-d5f3-4e38-8752-ad22cf135612_720x900.jpg?v=1680072263"
        ],
        "price": 2200.0,
        "inStock": true,
        "type": "cargos",
        "reviews": 56,
        "productDescription": "Wear-with-everything pants in our signature straight fit. Designed in comfortable twill fabric made with drawstring waist band, Advanced Stretch, Featuring cargo pockets and back pockets."
      },
      {
        "id": "11",
        "name": "Washed Denim Cargo Jeans",
        "images": [
          "https://thehangerpakistan.com/cdn/shop/files/IMG-2088_720x864.jpg?v=1696374540",
          "https://thehangerpakistan.com/cdn/shop/files/IMG-2089_720x864.jpg?v=1696374540",
          "https://thehangerpakistan.com/cdn/shop/files/IMG-2091_720x864.jpg?v=1696371684"
        ],
        "price": 2200.0,
        "inStock": true,
        "type": "trousers",
        "reviews": 2,
        "productDescription": "Wear-with-everything pants in our signature straight fit. Designed in comfortable twill fabric made with drawstring waist band, Advanced Stretch, Featuring cargo pockets and back pockets."
      }
    ],
    "T-shirts": [
      {
        "id": "17",
        "name": "Motor Drip",
        "images": [
          "https://thehangerpakistan.com/cdn/shop/files/IMG-2133_720x1069.jpg?v=1696426408",
          "https://thehangerpakistan.com/cdn/shop/files/IMG-2139_720x1080.jpg?v=1696426417",
          "https://thehangerpakistan.com/cdn/shop/files/IMG-2138_720x1080.jpg?v=1696426417"
        ],
        "price": 1399.0,
        "inStock": true,
        "type": "cargos",
        "reviews": 2,
        "productDescription": "Super soft and ultra comfortable oversized t-shirt with round neck & drop shoulders featuring a screen print graphics."
      },
      {
        "id": "13",
        "name": "Heavyweight Champtions",
        "images": [
          "https://thehangerpakistan.com/cdn/shop/files/4A612A6E-E8CA-4DFD-89F7-7DB9EA04A2D5_720x900.jpg?v=1696434474",
          "https://thehangerpakistan.com/cdn/shop/files/D8E755DC-0580-4A11-AE80-C5D151D17C9E_720x918.jpg?v=1696434474",
          "https://thehangerpakistan.com/cdn/shop/files/B23A60C1-07EE-45AE-84D2-1E3227360856_720x864.jpg?v=1696434474"
        ],
        "price": 1380.0,
        "inStock": true,
        "type": "cargos",
        "reviews": 15,
        "productDescription": "Super soft and ultra comfortable oversized t-shirt with round neck & drop shoulders featuring a screen print graphics."
      }
    ],
    "Pink": [
      {
        "id": "15",
        "name": "Heart Cut-Out Rib Top Full",
        "images": [
          "https://thehangerpakistan.com/cdn/shop/files/55341F2B-5CAA-43AA-98D5-DCD86D31FD5C_720x900.jpg?v=1703557981",
          "https://thehangerpakistan.com/cdn/shop/files/511E45A6-0A16-47E4-AE5E-102B6A17FBF8_720x900.jpg?v=1703557981",
          "https://thehangerpakistan.com/cdn/shop/files/E7BB9E08-F8AA-4D42-ACF8-5D004E3D7184_720x900.jpg?v=1703557981"
        ],
        "price": 1249.0,
        "inStock": true,
        "type": "Casual",
        "reviews": 1,
        "productDescription": "Super soft and ultra-comfy, this ribbed knit top featuring a heart cut-out closure that follows half sleeves Slim Fit."
      },
      {
        "id": "14",
        "name": "Heart Cut-Out Rib Top",
        "images": [
          "https://thehangerpakistan.com/cdn/shop/files/image_d4ef7f4c-a26c-4d11-9f44-a46613fb8535_720x900.jpg?v=1687631100",
          "https://thehangerpakistan.com/cdn/shop/files/image_96e8e975-ef0e-4cee-8502-3527714d75b3_720x900.jpg?v=1687631100",
          "https://thehangerpakistan.com/cdn/shop/products/image_2a695aa6-a499-4251-b998-17385fac17ca_720x900.jpg?v=1687631092"
        ],
        "price": 1100.0,
        "inStock": true,
        "type": "Casual",
        "reviews": 12,
        "productDescription": "Super soft and ultra-comfy, this ribbed knit top featuring a heart cut-out closure that follows half sleeves Slim Fit."
      },

      {
        "id": "16",
        "name": "Cosmic",
        "images": [
          "https://thehangerpakistan.com/cdn/shop/files/FDCD218E-B45D-4CAB-93F5-17211C6A0D18_720x864.jpg?v=1696347426",
          "https://thehangerpakistan.com/cdn/shop/files/CF37EF44-5B14-42D0-AFC9-81243D8C6D29_720x864.jpg?v=1696347426",
          "https://thehangerpakistan.com/cdn/shop/files/0F7CDA89-D919-4F14-B440-457D14E3EDA1_720x864.jpg?v=1696347425"
        ],
        "price": 1000.0,
        "inStock": true,
        "type": "Casual",
        "reviews": 1,
        "productDescription": "Unbelievably soft and comfy, this baby tee is made with premium cotton fabric and features a graphic print."
      }
    ],
    "Headwear": [
      {
        "id": "17",
        "name": "Super Suede Cap//01",
        "images": [
          "https://thehangerpakistan.com/cdn/shop/products/image_a07e8a80-12be-4251-91ad-5799f60421ac_720x720.jpg?v=1681356105",
          "https://thehangerpakistan.com/cdn/shop/products/image_c3d4c2a1-de9c-412e-93a9-ae9fd5b21325_720x900.jpg?v=1681356105",
          "https://thehangerpakistan.com/cdn/shop/products/image_56d6bd09-a505-4331-8a73-ebe443670994_720x900.jpg?v=1681356105"
        ],
        "price": 1500.0,
        "inStock": true,
        "type": "Casual",
        "reviews": 12,
        "productDescription": "Uber cool suede premium baseball cap by The Hanger Featuring a bold embroidered design on the front of the cap. Add attitude with this cap to your look for those fashion-forward finishing touches."
      },
      {
        "id": "18",
        "name": "Super Suede Cap//02",
        "images": [
          "https://thehangerpakistan.com/cdn/shop/products/image_4dff8bed-8991-4d88-9149-80be86a443f2_720x720.jpg?v=1681356064",
          "https://thehangerpakistan.com/cdn/shop/products/image_bf095f81-d15f-48f6-9faa-3009a1670452_720x900.jpg?v=1681356023",
          "https://thehangerpakistan.com/cdn/shop/products/image_20f0d69c-14bf-4f09-bd9b-893db3b7d334_720x900.jpg?v=1681356023"
        ],
        "price": 1400.0,
        "inStock": true,
        "type": "Casual",
        "reviews": 1,
        "productDescription": "Uber cool suede premium baseball cap by The Hanger Featuring a bold embroidered design on the front of the cap. Add attitude with this cap to your look for those fashion-forward finishing touches."
      }
    ]
  }
}
